{
	"json_content": {
		"technique": "technique",
		"findings": "findings",
		"parenchyma": "parenchyma",
		"mediastinum_vessels": "mediastinum_vessels",
		"mediastinum_trachea": "mediastinum_trachea",
		"mediastinum_oesophagus": "mediastinum_oesophagus",
		"mediastinum_thymus": "mediastinum_thymus",
		"mediastinum_lymph_nodes": "mediastinum_lymph_nodes",
		"heart": "heart",
		"pleura": "pleura",
		"bones": "bones",
		"after_iv_contrast": "after_iv_contrast",
		"impression": "impression",
		"trachea": "trachea",
		"diaphragm": "diaphragm",
		"lungs": "lungs",
		"bony_thorax": "bony_thorax",
		"rif_resistance_not_detected": 1,
		"rif_resistance_detected": 1,
		"rif_resistance_indeterminate": 1,
		"mtb_not_detected": 1,
		"invalid": 1,
		"sars_cov": 1,
		"dengue_ns": 1,
		"tb_hospital": "tb_hospital",
		"tb_registration_number": "tb_registration_number",
		"dr_tb_registration_number": "dr_tb_registration_number",
		"e_tb_registration_number": "e_tb_registration_number",
		"diagnosis": 1,
		"follow_up_month": "follow_up_month",
		"other_test_microscopy": "other_test_microscopy",
		"other_gene_xpert": "other_gene_xpert",
		"other_culture": "other_culture",
		"other_dst": "other_dst",
		"first_line_inh": "first_line_inh",
		"first_line_rif": "first_line_rif",
		"second_line_sr": "second_line_sr",
		"second_line_resistance_level": "second_line_resistance_level",
		"second_recommendation": "second_recommendation",
		"second_line_km_am_cm": "second_line_km_am_cm",
		"second_line_km_cm": "second_line_km_cm",
		"second_line_low_height_km_cm": "second_line_low_height_km_cm",
		"non_interpretable": "non_interpretable",
		"flq_low_resistance": "flq_low_resistance",
		"flq_high_resistance": "flq_high_resistance",
		"flq_low_to_high": "flq_low_to_high",
		"isl_resistant_km_am_cm": "isl_resistant_km_am_cm",
		"isl_resistant_km_cm": "isl_resistant_km_cm",
		"isl_resistant_low_km_to_high_cm": "isl_resistant_low_km_to_high_cm",
		"specimen_identification_number": "specimen_identification_number",
		"referral_center": "referral_center",
		"type_patient": "type_patient",
		"last_covid_test_center": "last_covid_test_center",
		"specimen": "specimen",
		"preservative": "preservative",
		"gene_xpert_hospital": "gene_xpert_hospital",
		"reference_laboratory_specimen_id": "reference_laboratory_specimen_id",
		"sars_cov_positive": 1,
		"presumptive_pos": 1,
		"sars_covnegative": 1,
		"cov_invalid": 1,
		"afb_no_found": 1,
		"afb_scanty": 1,
		"afb_scanty_one": 1,
		"afb_scanty_two": 1,
		"afb_scanty_three": 1,
		"date_specimen_collection": "2025-10-18 19:05:45",
		"date_specimen_received": "2025-10-18 19:05:45",
		"last_covid_test_date": "2025-10-18 19:05:45"
	},
	"created_by_id": 15,
	"comment": "test",
	"prescription_date": "2025-08-24"
}
